social_gpt/__init__.py
social_gpt/ingestion/__init__.py
social_gpt/ingestion/indexer.py
social_gpt/ingestion/ingestion.py
social_gpt/ingestion/scraper/__init__.py
social_gpt/ingestion/scraper/linkedin_scraper.py
social_gpt/ingestion/scraper/scraper_factory.py
social_gpt/ingestion/scraper/social_scraper.py
social_gpt/ingestion/scraper/topmate_queries_scraper.py
social_gpt/ingestion/scraper/topmate_scraper.py
social_gpt/ingestion/scraper/twitter_scraper.py
social_gpt/ingestion/scraper/youtube_scraper.py
social_gpt/query/__init__.py
social_gpt/query/query_helper.py
social_gpt-0.0.17.dist-info/LICENSE
social_gpt-0.0.17.dist-info/METADATA
social_gpt-0.0.17.dist-info/WHEEL
social_gpt-0.0.17.dist-info/top_level.txt
social_gpt-0.0.17.dist-info/RECORD
