Metadata-Version: 2.1
Name: social-gpt
Version: 0.0.17
Summary: Social gpt
Home-page: https://github.com/topmate-io/social_gpt
Author: dinesh1301
Author-email: dinesh@topmate.io
Classifier: Programming Language :: Python :: 3
Classifier: License :: OSI Approved :: MIT License
Classifier: Operating System :: OS Independent
License-File: LICENSE
Requires-Dist: aiobotocore
Requires-Dist: aiohttp
Requires-Dist: aioitertools
Requires-Dist: aiosignal
Requires-Dist: appnope
Requires-Dist: asttokens
Requires-Dist: async-timeout
Requires-Dist: attrs
Requires-Dist: backcall
Requires-Dist: bleach
Requires-Dist: botocore
Requires-Dist: build
Requires-Dist: cachetools
Requires-Dist: certifi
Requires-Dist: charset-normalizer
Requires-Dist: dataclasses-json
Requires-Dist: decorator
Requires-Dist: docutils
Requires-Dist: executing
Requires-Dist: frozenlist
Requires-Dist: fsspec
Requires-Dist: google-api-core
Requires-Dist: google-api-python-client
Requires-Dist: google-auth
Requires-Dist: google-auth-httplib2
Requires-Dist: googleapis-common-protos
Requires-Dist: httplib2
Requires-Dist: idna
Requires-Dist: importlib-metadata
Requires-Dist: ipython
Requires-Dist: jaraco.classes
Requires-Dist: jedi
Requires-Dist: jmespath
Requires-Dist: keyring
Requires-Dist: langchain
Requires-Dist: langchainplus-sdk
Requires-Dist: llama-index
Requires-Dist: markdown-it-py
Requires-Dist: marshmallow
Requires-Dist: marshmallow-enum
Requires-Dist: matplotlib-inline
Requires-Dist: mdurl
Requires-Dist: more-itertools
Requires-Dist: multidict
Requires-Dist: mypy-extensions
Requires-Dist: numexpr
Requires-Dist: numpy
Requires-Dist: oauthlib
Requires-Dist: openai
Requires-Dist: openapi-schema-pydantic
Requires-Dist: packaging
Requires-Dist: pandas
Requires-Dist: parso
Requires-Dist: pexpect
Requires-Dist: pickleshare
Requires-Dist: pkginfo
Requires-Dist: progress
Requires-Dist: prompt-toolkit
Requires-Dist: protobuf
Requires-Dist: ptyprocess
Requires-Dist: pure-eval
Requires-Dist: pyasn1
Requires-Dist: pyasn1-modules
Requires-Dist: pydantic
Requires-Dist: Pygments
Requires-Dist: pyparsing
Requires-Dist: pyproject-hooks
Requires-Dist: python-dateutil
Requires-Dist: python-dotenv
Requires-Dist: pytz
Requires-Dist: PyYAML
Requires-Dist: readme-renderer
Requires-Dist: regex
Requires-Dist: requests
Requires-Dist: requests-oauthlib
Requires-Dist: requests-toolbelt
Requires-Dist: rfc3986
Requires-Dist: rich
Requires-Dist: rsa
Requires-Dist: s3fs
Requires-Dist: six
Requires-Dist: social-gpt
Requires-Dist: SQLAlchemy
Requires-Dist: stack-data
Requires-Dist: tenacity
Requires-Dist: tiktoken
Requires-Dist: tqdm
Requires-Dist: traitlets
Requires-Dist: tweepy
Requires-Dist: twine
Requires-Dist: typing-inspect
Requires-Dist: typing-extensions
Requires-Dist: tzdata
Requires-Dist: uritemplate
Requires-Dist: urllib3
Requires-Dist: wcwidth
Requires-Dist: webencodings
Requires-Dist: wrapt
Requires-Dist: yarl
Requires-Dist: youtube-transcript-api
Requires-Dist: zipp
